{
    "total": [
        {
            "id": "61550196861533",
            "count": 0
        },
        {
            "id": "61550545247516",
            "count": 0
        },
        {
            "id": "61551398277544",
            "count": 0
        },
        {
            "id": "61551804899310",
            "count": 0
        },
        {
            "id": "61553757497270",
            "count": 0
        },
        {
            "id": "61554822740643",
            "count": 0
        },
        {
            "id": "61555708343072",
            "count": 0
        },
        {
            "id": "61556697489658",
            "count": 0
        },
        {
            "id": "61556999132139",
            "count": 0
        },
        {
            "id": "100001080626181",
            "count": 0
        },
        {
            "id": "100003188048236",
            "count": 0
        },
        {
            "id": "100004036495131",
            "count": 0
        },
        {
            "id": "100004071712976",
            "count": 0
        },
        {
            "id": "100004991921716",
            "count": 0
        },
        {
            "id": "100005192889597",
            "count": 0
        },
        {
            "id": "100005394919312",
            "count": 0
        },
        {
            "id": "100006182554227",
            "count": 0
        },
        {
            "id": "100006445728149",
            "count": 0
        },
        {
            "id": "100006628692725",
            "count": 0
        },
        {
            "id": "100007142200758",
            "count": 0
        },
        {
            "id": "100007243623558",
            "count": 0
        },
        {
            "id": "100007944003352",
            "count": 0
        },
        {
            "id": "100008112798867",
            "count": 0
        },
        {
            "id": "100008180895855",
            "count": 0
        },
        {
            "id": "100008220692888",
            "count": 0
        },
        {
            "id": "100008886409504",
            "count": 0
        },
        {
            "id": "100009241010237",
            "count": 0
        },
        {
            "id": "100009725773511",
            "count": 0
        },
        {
            "id": "100010042634393",
            "count": 0
        },
        {
            "id": "100010089272873",
            "count": 0
        },
        {
            "id": "100010408450915",
            "count": 0
        },
        {
            "id": "100010741080450",
            "count": 0
        },
        {
            "id": "100010845849621",
            "count": 0
        },
        {
            "id": "100011312407386",
            "count": 0
        },
        {
            "id": "100011575547183",
            "count": 0
        },
        {
            "id": "100011644392112",
            "count": 0
        },
        {
            "id": "100011742282005",
            "count": 0
        },
        {
            "id": "100012218052710",
            "count": 0
        },
        {
            "id": "100013271716690",
            "count": 0
        },
        {
            "id": "100013740677630",
            "count": 0
        },
        {
            "id": "100014404544077",
            "count": 0
        },
        {
            "id": "100014756829256",
            "count": 0
        },
        {
            "id": "100015055261621",
            "count": 0
        },
        {
            "id": "100015073093214",
            "count": 0
        },
        {
            "id": "100017755023384",
            "count": 0
        },
        {
            "id": "100019604800844",
            "count": 0
        },
        {
            "id": "100020691924137",
            "count": 0
        },
        {
            "id": "100021582884859",
            "count": 3
        },
        {
            "id": "100022420052469",
            "count": 0
        },
        {
            "id": "100022844202718",
            "count": 1
        },
        {
            "id": "100023421220155",
            "count": 0
        },
        {
            "id": "100023633361205",
            "count": 0
        },
        {
            "id": "100025480897356",
            "count": 0
        },
        {
            "id": "100025883260768",
            "count": 0
        },
        {
            "id": "100026902672495",
            "count": 0
        },
        {
            "id": "100028164410191",
            "count": 0
        },
        {
            "id": "100028789522042",
            "count": 0
        },
        {
            "id": "100029133490208",
            "count": 0
        },
        {
            "id": "100029854263272",
            "count": 0
        },
        {
            "id": "100032151361136",
            "count": 0
        },
        {
            "id": "100032350513948",
            "count": 0
        },
        {
            "id": "100032950879419",
            "count": 0
        },
        {
            "id": "100033211024828",
            "count": 0
        },
        {
            "id": "100034230953926",
            "count": 0
        },
        {
            "id": "100034451535088",
            "count": 0
        },
        {
            "id": "100034945937949",
            "count": 0
        },
        {
            "id": "100035030624442",
            "count": 0
        },
        {
            "id": "100035197935696",
            "count": 0
        },
        {
            "id": "100035316009468",
            "count": 1
        },
        {
            "id": "100035590219959",
            "count": 0
        },
        {
            "id": "100035850820856",
            "count": 0
        },
        {
            "id": "100036596419691",
            "count": 0
        },
        {
            "id": "100037211391552",
            "count": 0
        },
        {
            "id": "100038579101337",
            "count": 0
        },
        {
            "id": "100038687885409",
            "count": 0
        },
        {
            "id": "100039035295569",
            "count": 0
        },
        {
            "id": "100039251630483",
            "count": 0
        },
        {
            "id": "100040049991984",
            "count": 0
        },
        {
            "id": "100040118794281",
            "count": 1
        },
        {
            "id": "100041312664023",
            "count": 0
        },
        {
            "id": "100041450375219",
            "count": 0
        },
        {
            "id": "100041981624654",
            "count": 0
        },
        {
            "id": "100041997488371",
            "count": 0
        },
        {
            "id": "100042233011438",
            "count": 0
        },
        {
            "id": "100042334133260",
            "count": 0
        },
        {
            "id": "100042497810862",
            "count": 0
        },
        {
            "id": "100042981615006",
            "count": 0
        },
        {
            "id": "100043479736423",
            "count": 0
        },
        {
            "id": "100043541993245",
            "count": 0
        },
        {
            "id": "100043993261673",
            "count": 0
        },
        {
            "id": "100044242395929",
            "count": 1
        },
        {
            "id": "100044260131264",
            "count": 0
        },
        {
            "id": "100046613271899",
            "count": 0
        },
        {
            "id": "100047067821774",
            "count": 0
        },
        {
            "id": "100047268392751",
            "count": 0
        },
        {
            "id": "100047404650481",
            "count": 0
        },
        {
            "id": "100047840051740",
            "count": 0
        },
        {
            "id": "100047937260261",
            "count": 0
        },
        {
            "id": "100047992532734",
            "count": 0
        },
        {
            "id": "100048859625208",
            "count": 0
        },
        {
            "id": "100049876341304",
            "count": 0
        },
        {
            "id": "100052198092641",
            "count": 0
        },
        {
            "id": "100052306357269",
            "count": 0
        },
        {
            "id": "100054391727796",
            "count": 0
        },
        {
            "id": "100055522392482",
            "count": 0
        },
        {
            "id": "100055836259425",
            "count": 0
        },
        {
            "id": "100057144399887",
            "count": 0
        },
        {
            "id": "100057713543346",
            "count": 0
        },
        {
            "id": "100060760845545",
            "count": 0
        },
        {
            "id": "100061456423468",
            "count": 0
        },
        {
            "id": "100063704975117",
            "count": 0
        },
        {
            "id": "100064178019519",
            "count": 0
        },
        {
            "id": "100064441362506",
            "count": 0
        },
        {
            "id": "100066346686017",
            "count": 0
        },
        {
            "id": "100066769025877",
            "count": 0
        },
        {
            "id": "100067070419414",
            "count": 0
        },
        {
            "id": "100067091792794",
            "count": 0
        },
        {
            "id": "100067772375493",
            "count": 0
        },
        {
            "id": "100067868103564",
            "count": 0
        },
        {
            "id": "100070285163469",
            "count": 0
        },
        {
            "id": "100071950271132",
            "count": 0
        },
        {
            "id": "100072163815434",
            "count": 0
        },
        {
            "id": "100072935336978",
            "count": 0
        },
        {
            "id": "100073077278766",
            "count": 0
        },
        {
            "id": "100073471425078",
            "count": 0
        },
        {
            "id": "100073631663339",
            "count": 0
        },
        {
            "id": "100073966322300",
            "count": 0
        },
        {
            "id": "100076353803572",
            "count": 0
        },
        {
            "id": "100077074060442",
            "count": 0
        },
        {
            "id": "100077755544933",
            "count": 0
        },
        {
            "id": "100077817561441",
            "count": 0
        },
        {
            "id": "100077994264970",
            "count": 0
        },
        {
            "id": "100079642154944",
            "count": 0
        },
        {
            "id": "100080272183127",
            "count": 1
        },
        {
            "id": "100082096437582",
            "count": 0
        },
        {
            "id": "100082394559679",
            "count": 0
        },
        {
            "id": "100082526254131",
            "count": 0
        },
        {
            "id": "100083186740550",
            "count": 0
        },
        {
            "id": "100086442993036",
            "count": 0
        },
        {
            "id": "100087131042120",
            "count": 0
        },
        {
            "id": "100087822962259",
            "count": 0
        },
        {
            "id": "100089808414810",
            "count": 0
        },
        {
            "id": "100090494147952",
            "count": 0
        },
        {
            "id": "100091145157223",
            "count": 0
        },
        {
            "id": "100092674343729",
            "count": 0
        },
        {
            "id": "100092960021775",
            "count": 0
        },
        {
            "id": "100075355876941",
            "count": 1
        },
        {
            "id": "100031188014522",
            "count": 1
        }
    ],
    "week": [
        {
            "id": "61550196861533",
            "count": 0
        },
        {
            "id": "61550545247516",
            "count": 0
        },
        {
            "id": "61551398277544",
            "count": 0
        },
        {
            "id": "61551804899310",
            "count": 0
        },
        {
            "id": "61553757497270",
            "count": 0
        },
        {
            "id": "61554822740643",
            "count": 0
        },
        {
            "id": "61555708343072",
            "count": 0
        },
        {
            "id": "61556697489658",
            "count": 0
        },
        {
            "id": "61556999132139",
            "count": 0
        },
        {
            "id": "100001080626181",
            "count": 0
        },
        {
            "id": "100003188048236",
            "count": 0
        },
        {
            "id": "100004036495131",
            "count": 0
        },
        {
            "id": "100004071712976",
            "count": 0
        },
        {
            "id": "100004991921716",
            "count": 0
        },
        {
            "id": "100005192889597",
            "count": 0
        },
        {
            "id": "100005394919312",
            "count": 0
        },
        {
            "id": "100006182554227",
            "count": 0
        },
        {
            "id": "100006445728149",
            "count": 0
        },
        {
            "id": "100006628692725",
            "count": 0
        },
        {
            "id": "100007142200758",
            "count": 0
        },
        {
            "id": "100007243623558",
            "count": 0
        },
        {
            "id": "100007944003352",
            "count": 0
        },
        {
            "id": "100008112798867",
            "count": 0
        },
        {
            "id": "100008180895855",
            "count": 0
        },
        {
            "id": "100008220692888",
            "count": 0
        },
        {
            "id": "100008886409504",
            "count": 0
        },
        {
            "id": "100009241010237",
            "count": 0
        },
        {
            "id": "100009725773511",
            "count": 0
        },
        {
            "id": "100010042634393",
            "count": 0
        },
        {
            "id": "100010089272873",
            "count": 0
        },
        {
            "id": "100010408450915",
            "count": 0
        },
        {
            "id": "100010741080450",
            "count": 0
        },
        {
            "id": "100010845849621",
            "count": 0
        },
        {
            "id": "100011312407386",
            "count": 0
        },
        {
            "id": "100011575547183",
            "count": 0
        },
        {
            "id": "100011644392112",
            "count": 0
        },
        {
            "id": "100011742282005",
            "count": 0
        },
        {
            "id": "100012218052710",
            "count": 0
        },
        {
            "id": "100013271716690",
            "count": 0
        },
        {
            "id": "100013740677630",
            "count": 0
        },
        {
            "id": "100014404544077",
            "count": 0
        },
        {
            "id": "100014756829256",
            "count": 0
        },
        {
            "id": "100015055261621",
            "count": 0
        },
        {
            "id": "100015073093214",
            "count": 0
        },
        {
            "id": "100017755023384",
            "count": 0
        },
        {
            "id": "100019604800844",
            "count": 0
        },
        {
            "id": "100020691924137",
            "count": 0
        },
        {
            "id": "100021582884859",
            "count": 3
        },
        {
            "id": "100022420052469",
            "count": 0
        },
        {
            "id": "100022844202718",
            "count": 1
        },
        {
            "id": "100023421220155",
            "count": 0
        },
        {
            "id": "100023633361205",
            "count": 0
        },
        {
            "id": "100025480897356",
            "count": 0
        },
        {
            "id": "100025883260768",
            "count": 0
        },
        {
            "id": "100026902672495",
            "count": 0
        },
        {
            "id": "100028164410191",
            "count": 0
        },
        {
            "id": "100028789522042",
            "count": 0
        },
        {
            "id": "100029133490208",
            "count": 0
        },
        {
            "id": "100029854263272",
            "count": 0
        },
        {
            "id": "100032151361136",
            "count": 0
        },
        {
            "id": "100032350513948",
            "count": 0
        },
        {
            "id": "100032950879419",
            "count": 0
        },
        {
            "id": "100033211024828",
            "count": 0
        },
        {
            "id": "100034230953926",
            "count": 0
        },
        {
            "id": "100034451535088",
            "count": 0
        },
        {
            "id": "100034945937949",
            "count": 0
        },
        {
            "id": "100035030624442",
            "count": 0
        },
        {
            "id": "100035197935696",
            "count": 0
        },
        {
            "id": "100035316009468",
            "count": 1
        },
        {
            "id": "100035590219959",
            "count": 0
        },
        {
            "id": "100035850820856",
            "count": 0
        },
        {
            "id": "100036596419691",
            "count": 0
        },
        {
            "id": "100037211391552",
            "count": 0
        },
        {
            "id": "100038579101337",
            "count": 0
        },
        {
            "id": "100038687885409",
            "count": 0
        },
        {
            "id": "100039035295569",
            "count": 0
        },
        {
            "id": "100039251630483",
            "count": 0
        },
        {
            "id": "100040049991984",
            "count": 0
        },
        {
            "id": "100040118794281",
            "count": 1
        },
        {
            "id": "100041312664023",
            "count": 0
        },
        {
            "id": "100041450375219",
            "count": 0
        },
        {
            "id": "100041981624654",
            "count": 0
        },
        {
            "id": "100041997488371",
            "count": 0
        },
        {
            "id": "100042233011438",
            "count": 0
        },
        {
            "id": "100042334133260",
            "count": 0
        },
        {
            "id": "100042497810862",
            "count": 0
        },
        {
            "id": "100042981615006",
            "count": 0
        },
        {
            "id": "100043479736423",
            "count": 0
        },
        {
            "id": "100043541993245",
            "count": 0
        },
        {
            "id": "100043993261673",
            "count": 0
        },
        {
            "id": "100044242395929",
            "count": 1
        },
        {
            "id": "100044260131264",
            "count": 0
        },
        {
            "id": "100046613271899",
            "count": 0
        },
        {
            "id": "100047067821774",
            "count": 0
        },
        {
            "id": "100047268392751",
            "count": 0
        },
        {
            "id": "100047404650481",
            "count": 0
        },
        {
            "id": "100047840051740",
            "count": 0
        },
        {
            "id": "100047937260261",
            "count": 0
        },
        {
            "id": "100047992532734",
            "count": 0
        },
        {
            "id": "100048859625208",
            "count": 0
        },
        {
            "id": "100049876341304",
            "count": 0
        },
        {
            "id": "100052198092641",
            "count": 0
        },
        {
            "id": "100052306357269",
            "count": 0
        },
        {
            "id": "100054391727796",
            "count": 0
        },
        {
            "id": "100055522392482",
            "count": 0
        },
        {
            "id": "100055836259425",
            "count": 0
        },
        {
            "id": "100057144399887",
            "count": 0
        },
        {
            "id": "100057713543346",
            "count": 0
        },
        {
            "id": "100060760845545",
            "count": 0
        },
        {
            "id": "100061456423468",
            "count": 0
        },
        {
            "id": "100063704975117",
            "count": 0
        },
        {
            "id": "100064178019519",
            "count": 0
        },
        {
            "id": "100064441362506",
            "count": 0
        },
        {
            "id": "100066346686017",
            "count": 0
        },
        {
            "id": "100066769025877",
            "count": 0
        },
        {
            "id": "100067070419414",
            "count": 0
        },
        {
            "id": "100067091792794",
            "count": 0
        },
        {
            "id": "100067772375493",
            "count": 0
        },
        {
            "id": "100067868103564",
            "count": 0
        },
        {
            "id": "100070285163469",
            "count": 0
        },
        {
            "id": "100071950271132",
            "count": 0
        },
        {
            "id": "100072163815434",
            "count": 0
        },
        {
            "id": "100072935336978",
            "count": 0
        },
        {
            "id": "100073077278766",
            "count": 0
        },
        {
            "id": "100073471425078",
            "count": 0
        },
        {
            "id": "100073631663339",
            "count": 0
        },
        {
            "id": "100073966322300",
            "count": 0
        },
        {
            "id": "100076353803572",
            "count": 0
        },
        {
            "id": "100077074060442",
            "count": 0
        },
        {
            "id": "100077755544933",
            "count": 0
        },
        {
            "id": "100077817561441",
            "count": 0
        },
        {
            "id": "100077994264970",
            "count": 0
        },
        {
            "id": "100079642154944",
            "count": 0
        },
        {
            "id": "100080272183127",
            "count": 1
        },
        {
            "id": "100082096437582",
            "count": 0
        },
        {
            "id": "100082394559679",
            "count": 0
        },
        {
            "id": "100082526254131",
            "count": 0
        },
        {
            "id": "100083186740550",
            "count": 0
        },
        {
            "id": "100086442993036",
            "count": 0
        },
        {
            "id": "100087131042120",
            "count": 0
        },
        {
            "id": "100087822962259",
            "count": 0
        },
        {
            "id": "100089808414810",
            "count": 0
        },
        {
            "id": "100090494147952",
            "count": 0
        },
        {
            "id": "100091145157223",
            "count": 0
        },
        {
            "id": "100092674343729",
            "count": 0
        },
        {
            "id": "100092960021775",
            "count": 0
        },
        {
            "id": "100075355876941",
            "count": 1
        },
        {
            "id": "100031188014522",
            "count": 1
        }
    ],
    "day": [
        {
            "id": "61550196861533",
            "count": 0
        },
        {
            "id": "61550545247516",
            "count": 0
        },
        {
            "id": "61551398277544",
            "count": 0
        },
        {
            "id": "61551804899310",
            "count": 0
        },
        {
            "id": "61553757497270",
            "count": 0
        },
        {
            "id": "61554822740643",
            "count": 0
        },
        {
            "id": "61555708343072",
            "count": 0
        },
        {
            "id": "61556697489658",
            "count": 0
        },
        {
            "id": "61556999132139",
            "count": 0
        },
        {
            "id": "100001080626181",
            "count": 0
        },
        {
            "id": "100003188048236",
            "count": 0
        },
        {
            "id": "100004036495131",
            "count": 0
        },
        {
            "id": "100004071712976",
            "count": 0
        },
        {
            "id": "100004991921716",
            "count": 0
        },
        {
            "id": "100005192889597",
            "count": 0
        },
        {
            "id": "100005394919312",
            "count": 0
        },
        {
            "id": "100006182554227",
            "count": 0
        },
        {
            "id": "100006445728149",
            "count": 0
        },
        {
            "id": "100006628692725",
            "count": 0
        },
        {
            "id": "100007142200758",
            "count": 0
        },
        {
            "id": "100007243623558",
            "count": 0
        },
        {
            "id": "100007944003352",
            "count": 0
        },
        {
            "id": "100008112798867",
            "count": 0
        },
        {
            "id": "100008180895855",
            "count": 0
        },
        {
            "id": "100008220692888",
            "count": 0
        },
        {
            "id": "100008886409504",
            "count": 0
        },
        {
            "id": "100009241010237",
            "count": 0
        },
        {
            "id": "100009725773511",
            "count": 0
        },
        {
            "id": "100010042634393",
            "count": 0
        },
        {
            "id": "100010089272873",
            "count": 0
        },
        {
            "id": "100010408450915",
            "count": 0
        },
        {
            "id": "100010741080450",
            "count": 0
        },
        {
            "id": "100010845849621",
            "count": 0
        },
        {
            "id": "100011312407386",
            "count": 0
        },
        {
            "id": "100011575547183",
            "count": 0
        },
        {
            "id": "100011644392112",
            "count": 0
        },
        {
            "id": "100011742282005",
            "count": 0
        },
        {
            "id": "100012218052710",
            "count": 0
        },
        {
            "id": "100013271716690",
            "count": 0
        },
        {
            "id": "100013740677630",
            "count": 0
        },
        {
            "id": "100014404544077",
            "count": 0
        },
        {
            "id": "100014756829256",
            "count": 0
        },
        {
            "id": "100015055261621",
            "count": 0
        },
        {
            "id": "100015073093214",
            "count": 0
        },
        {
            "id": "100017755023384",
            "count": 0
        },
        {
            "id": "100019604800844",
            "count": 0
        },
        {
            "id": "100020691924137",
            "count": 0
        },
        {
            "id": "100021582884859",
            "count": 3
        },
        {
            "id": "100022420052469",
            "count": 0
        },
        {
            "id": "100022844202718",
            "count": 1
        },
        {
            "id": "100023421220155",
            "count": 0
        },
        {
            "id": "100023633361205",
            "count": 0
        },
        {
            "id": "100025480897356",
            "count": 0
        },
        {
            "id": "100025883260768",
            "count": 0
        },
        {
            "id": "100026902672495",
            "count": 0
        },
        {
            "id": "100028164410191",
            "count": 0
        },
        {
            "id": "100028789522042",
            "count": 0
        },
        {
            "id": "100029133490208",
            "count": 0
        },
        {
            "id": "100029854263272",
            "count": 0
        },
        {
            "id": "100032151361136",
            "count": 0
        },
        {
            "id": "100032350513948",
            "count": 0
        },
        {
            "id": "100032950879419",
            "count": 0
        },
        {
            "id": "100033211024828",
            "count": 0
        },
        {
            "id": "100034230953926",
            "count": 0
        },
        {
            "id": "100034451535088",
            "count": 0
        },
        {
            "id": "100034945937949",
            "count": 0
        },
        {
            "id": "100035030624442",
            "count": 0
        },
        {
            "id": "100035197935696",
            "count": 0
        },
        {
            "id": "100035316009468",
            "count": 1
        },
        {
            "id": "100035590219959",
            "count": 0
        },
        {
            "id": "100035850820856",
            "count": 0
        },
        {
            "id": "100036596419691",
            "count": 0
        },
        {
            "id": "100037211391552",
            "count": 0
        },
        {
            "id": "100038579101337",
            "count": 0
        },
        {
            "id": "100038687885409",
            "count": 0
        },
        {
            "id": "100039035295569",
            "count": 0
        },
        {
            "id": "100039251630483",
            "count": 0
        },
        {
            "id": "100040049991984",
            "count": 0
        },
        {
            "id": "100040118794281",
            "count": 1
        },
        {
            "id": "100041312664023",
            "count": 0
        },
        {
            "id": "100041450375219",
            "count": 0
        },
        {
            "id": "100041981624654",
            "count": 0
        },
        {
            "id": "100041997488371",
            "count": 0
        },
        {
            "id": "100042233011438",
            "count": 0
        },
        {
            "id": "100042334133260",
            "count": 0
        },
        {
            "id": "100042497810862",
            "count": 0
        },
        {
            "id": "100042981615006",
            "count": 0
        },
        {
            "id": "100043479736423",
            "count": 0
        },
        {
            "id": "100043541993245",
            "count": 0
        },
        {
            "id": "100043993261673",
            "count": 0
        },
        {
            "id": "100044242395929",
            "count": 1
        },
        {
            "id": "100044260131264",
            "count": 0
        },
        {
            "id": "100046613271899",
            "count": 0
        },
        {
            "id": "100047067821774",
            "count": 0
        },
        {
            "id": "100047268392751",
            "count": 0
        },
        {
            "id": "100047404650481",
            "count": 0
        },
        {
            "id": "100047840051740",
            "count": 0
        },
        {
            "id": "100047937260261",
            "count": 0
        },
        {
            "id": "100047992532734",
            "count": 0
        },
        {
            "id": "100048859625208",
            "count": 0
        },
        {
            "id": "100049876341304",
            "count": 0
        },
        {
            "id": "100052198092641",
            "count": 0
        },
        {
            "id": "100052306357269",
            "count": 0
        },
        {
            "id": "100054391727796",
            "count": 0
        },
        {
            "id": "100055522392482",
            "count": 0
        },
        {
            "id": "100055836259425",
            "count": 0
        },
        {
            "id": "100057144399887",
            "count": 0
        },
        {
            "id": "100057713543346",
            "count": 0
        },
        {
            "id": "100060760845545",
            "count": 0
        },
        {
            "id": "100061456423468",
            "count": 0
        },
        {
            "id": "100063704975117",
            "count": 0
        },
        {
            "id": "100064178019519",
            "count": 0
        },
        {
            "id": "100064441362506",
            "count": 0
        },
        {
            "id": "100066346686017",
            "count": 0
        },
        {
            "id": "100066769025877",
            "count": 0
        },
        {
            "id": "100067070419414",
            "count": 0
        },
        {
            "id": "100067091792794",
            "count": 0
        },
        {
            "id": "100067772375493",
            "count": 0
        },
        {
            "id": "100067868103564",
            "count": 0
        },
        {
            "id": "100070285163469",
            "count": 0
        },
        {
            "id": "100071950271132",
            "count": 0
        },
        {
            "id": "100072163815434",
            "count": 0
        },
        {
            "id": "100072935336978",
            "count": 0
        },
        {
            "id": "100073077278766",
            "count": 0
        },
        {
            "id": "100073471425078",
            "count": 0
        },
        {
            "id": "100073631663339",
            "count": 0
        },
        {
            "id": "100073966322300",
            "count": 0
        },
        {
            "id": "100076353803572",
            "count": 0
        },
        {
            "id": "100077074060442",
            "count": 0
        },
        {
            "id": "100077755544933",
            "count": 0
        },
        {
            "id": "100077817561441",
            "count": 0
        },
        {
            "id": "100077994264970",
            "count": 0
        },
        {
            "id": "100079642154944",
            "count": 0
        },
        {
            "id": "100080272183127",
            "count": 1
        },
        {
            "id": "100082096437582",
            "count": 0
        },
        {
            "id": "100082394559679",
            "count": 0
        },
        {
            "id": "100082526254131",
            "count": 0
        },
        {
            "id": "100083186740550",
            "count": 0
        },
        {
            "id": "100086442993036",
            "count": 0
        },
        {
            "id": "100087131042120",
            "count": 0
        },
        {
            "id": "100087822962259",
            "count": 0
        },
        {
            "id": "100089808414810",
            "count": 0
        },
        {
            "id": "100090494147952",
            "count": 0
        },
        {
            "id": "100091145157223",
            "count": 0
        },
        {
            "id": "100092674343729",
            "count": 0
        },
        {
            "id": "100092960021775",
            "count": 0
        },
        {
            "id": "100075355876941",
            "count": 1
        },
        {
            "id": "100031188014522",
            "count": 1
        }
    ],
    "time": 2
}